watertools/Set_Up_watertools.py
watertools/__init__.py
watertools/Collect/__init__.py
watertools/Collect/ALEXI/DataAccess.py
watertools/Collect/ALEXI/__init__.py
watertools/Collect/ALEXI/daily.py
watertools/Collect/ALEXI/monthly.py
watertools/Collect/ALEXI/weekly.py
watertools/Collect/ASCAT/DataAccess.py
watertools/Collect/ASCAT/__init__.py
watertools/Collect/ASCAT/daily.py
watertools/Collect/CFSR/DataAccess_CFSR.py
watertools/Collect/CFSR/Download_data_CFSR.py
watertools/Collect/CFSR/__init__.py
watertools/Collect/CFSR/daily.py
watertools/Collect/CHIRP/DataAccess.py
watertools/Collect/CHIRP/__init__.py
watertools/Collect/CHIRP/daily.py
watertools/Collect/CHIRPS/DataAccess.py
watertools/Collect/CHIRPS/__init__.py
watertools/Collect/CHIRPS/daily.py
watertools/Collect/CHIRPS/monthly.py
watertools/Collect/CMRSET/DataAccess.py
watertools/Collect/CMRSET/__init__.py
watertools/Collect/CMRSET/monthly.py
watertools/Collect/DEM/DataAccess_Hydro.py
watertools/Collect/DEM/DataAccess_SRTM.py
watertools/Collect/DEM/HydroSHED.py
watertools/Collect/DEM/HydroSHED_Acc.py
watertools/Collect/DEM/HydroSHED_Dir.py
watertools/Collect/DEM/SRTM.py
watertools/Collect/DEM/__init__.py
watertools/Collect/ECMWF/DataAccess.py
watertools/Collect/ECMWF/ECMWFdownload.py
watertools/Collect/ECMWF/__init__.py
watertools/Collect/ECMWF/daily.py
watertools/Collect/ECMWF/monthly.py
watertools/Collect/ESACCI/DataAccess.py
watertools/Collect/ESACCI/LU.py
watertools/Collect/ESACCI/__init__.py
watertools/Collect/ETmonitor/DataAccess.py
watertools/Collect/ETmonitor/ET_monthly.py
watertools/Collect/ETmonitor/ETpot_monthly.py
watertools/Collect/ETmonitor/Ei_monthly.py
watertools/Collect/ETmonitor/Es_monthly.py
watertools/Collect/ETmonitor/Ew_monthly.py
watertools/Collect/ETmonitor/Tr_monthly.py
watertools/Collect/ETmonitor/__init__.py
watertools/Collect/FEWS/ETpot_daily.py
watertools/Collect/FEWS/__init__.py
watertools/Collect/GEOS/DataAccess.py
watertools/Collect/GEOS/__init__.py
watertools-0.0.47.dist-info/LICENSE
watertools-0.0.47.dist-info/METADATA
watertools-0.0.47.dist-info/WHEEL
watertools-0.0.47.dist-info/top_level.txt
watertools-0.0.47.dist-info/RECORD
