Metadata-Version: 2.1
Name: watertools
Version: 0.0.47
Summary: Tools for data collecting and data processing of remote sensed data.
Home-page: https://github.com/TimHessels/watertools
Author: Tim Hessels
Author-email: timhessels@hotmail.com
License: UNKNOWN
Platform: UNKNOWN
Classifier: Programming Language :: Python :: 2
Classifier: Programming Language :: Python :: 3
Classifier: License :: OSI Approved :: Apache Software License
Classifier: Operating System :: OS Independent
License-File: LICENSE
